Workbook

Sheet Overview
A1: PM Workbook: [Назва проєкту]
A2: Один файл на проєкт. Копіюй цей шаблон для кожного нового ліда. Тут коротка картка проєкту, офер і зміст. Жовті клітинки заповнює PM, сірі рядки на інших листах є прикладами, їх видаляють.
A4: Картка проєкту
A5: Проєкт
A6: Клієнт | B6: ='Lead Handoff'!B6
A7: Етап | B7: Лід
A8: PM
A9: Старт
A10: Дедлайн
A11: Посилання
A12: Upwork
A13: Репозиторій
A14: Трекер (Jira / Linear)
A15: Канал комунікації
A16: Офер
A17: Тип контракту | B17: Hourly Rate
A18: Оцінка, год (In scope, з буфером) | B18: =Estimate!C7 -> 14.566667
A19: Ціна оферу, $ | B19: =Estimate!C8 -> 582.66667
A20: Зміни scope, $ (затверджені) | B20: ='Change Log'!B5 -> 640
A21: Поточна вартість, $ | B21: =B19+B20 -> 1222.6667
A22: Дата відправки оферу
A23: Статус оферу
A30: Лист | B30: Навіщо | C30: Хто заповнює
A31: Lead Handoff | B31: Вхідні дані від сейла і з Upwork. Заповнюється до першого дзвінка. | C31: Sales. PM доповнює після першого дзвінка
A32: Discovery | B32: Питання до клієнта за блоками і відповіді. Показує, що ще не з'ясовано. | C32: PM + Lead відповідає за блоки Інтеграції, Дані, Compliance
A33: Estimate | B33: WBS, оцінка в годинах, scope (In/Out), припущення. Звідси ціна оферу і Roadmap. | C33: Lead + Dev: задачі і години (Min/Likely/Max). PM: ставка, буфер, Scope, рядок демо
A34: Roadmap | B34: Етапи, milestones, залежності. Будується з WBS. | C34: PM + Lead перевіряє залежності та терміни
A35: Backlog | B35: Задачі для команди, прив'язані до WBS. | C35: PM створює задачі. Dev оновлює статус і факт годин. Lead додає технічні задачі
A36: Access & Env | B36: Чекліст доступів і середовищ. Без паролів. | C36: PM запитує у клієнта. Lead / Dev підтверджують отримання
A37: Daily Report | B37: Щоденні репорти, коли клієнт їх просить. | C37: Dev, кожен свій рядок
A38: Weekly Report | B38: Щотижневий репорт клієнту: зроблено, фічі, ризики, що потрібно від клієнта. | C38: PM, на основі Daily Report і Backlog
A39: Change Log | B39: Кожна зміна scope з впливом на години, гроші та дедлайн. | C39: PM + Lead оцінює вплив у годинах. Sales узгоджує, якщо зміна впливає на контракт
A40: Project Notes | B40: Журнал PM: дзвінки, рішення, питання, action items. | C40: PM
A42: Легенда
A43: Жовта клітинка | B43: Заповнює PM
A44: Сірий рядок | B44: Приклад формату, видалити перед роботою
A45: Біла клітинка з формулою | B45: Рахується сама, не редагувати

Sheet Lead Handoff
A1: Lead Handoff
A2: Що сейл знає про клієнта і проєкт на момент передачі PM. Дані з Upwork показують платоспроможність і серйозність клієнта ще до першого дзвінка. Заповнюється один раз, далі оновлюється за потреби.
A4: Поле | B4: Значення | C4: Примітка / звідки
A5: Про клієнта і проєкт
A6: Клієнт (компанія, контакт) | C6: Хто він, сайт, LinkedIn
A7: Проблема | C7: Що болить своїми словами клієнта
A8: Що хоче отримати | C8: Очікуваний результат
A9: Бюджет | C9: Озвучений або з job post
A10: Дедлайн | C10: Жорсткий чи бажаний, чим зумовлений
A11: Хто приймає рішення | C11: ЛПР, хто ще впливає
A12: Галузь / compliance | C12: Fintech, healthcare; HIPAA, PCI DSS, GDPR тощо
A13: Джерело ліда | C13: Upwork / рекомендація / інше
A14: Нотатки сейла | C14: Враження, ризики, домовленості
A15: Дані з Upwork
A16: Job post URL
A17: Назва job post
A18: Тип контракту | B18: Hourly Rate | C18: Hourly / Fixed
A19: Бюджет або rate у job post
A20: Payment verified | C20: Так / Ні
A21: Рейтинг клієнта | C21: Зірки
A22: Кількість відгуків
A23: Total spent | C23: $
A24: Hire rate | C24: %
A25: Кількість наймів
A26: Відкриті вакансії | C26: Скільки job posts активні зараз
A27: Країна / таймзона
A28: Member since
A29: Proposals на job post | C29: Конкуренція
A30: Interviewing | C30: Скільки вже на співбесідах
A31: Invites sent
A32: Connects витрачено
A33: Дата відправки proposal

Sheet Discovery
A1: Discovery Questionnaire
A2: Що треба з'ясувати в клієнта. Статус «Відкрите» означає діру в розумінні проєкту: до оферу таких питань у блоках, що впливають на оцінку, бути не повинно.
A4: Відкритих питань | B4: =COUNTIF(D7:D500,"Відкрите") -> 26 | C4: з них впливають на оцінку | D4: =COUNTIFS(D7:D500,"Відкрите",E7:E500,"Так") -> 26
A6: Блок | B6: Питання | C6: Відповідь | D6: Статус | E6: Впливає на оцінку | F6: Хто відповів | G6: Дата
A7: Бізнес-ціль | B7: Приклад: Яка частка заявок зараз обробляється вручну? | C7: ~70%, ціль знизити до 20% за 6 міс. | D7: Відповіли | E7: Так | F7: CTO клієнта | G7: 2026-10-14
A8: Бізнес-ціль | B8: Яку бізнес-проблему вирішуємо? Що станеться, якщо нічого не робити? | D8: Відкрите | E8: Так
A9: Бізнес-ціль | B9: Як вимірюватимемо успіх (метрики, цифри)? | D9: Відкрите | E9: Так
A10: Бізнес-ціль | B10: Чому саме зараз? Що зумовлює дедлайн? | D10: Відкрите | E10: Так
A11: Бізнес-ціль | B11: Хто ще залучений з боку клієнта і хто приймає фінальне рішення? | D11: Відкрите | E11: Так
A12: Бізнес-ціль | B12: Чи є бюджетна рамка або очікування по вартості? | D12: Відкрите | E12: Так
A13: Користувачі | B13: Хто користувачі (ролі)? Скільки їх зараз і через рік? | D13: Відкрите | E13: Так
A14: Користувачі | B14: Основні сценарії для кожної ролі? | D14: Відкрите | E14: Так
A15: Користувачі | B15: Платформи: web, mobile, internal tool? | D15: Відкрите | E15: Так
A16: Користувачі | B16: Мови, регіони, доступність (accessibility)? | D16: Відкрите | E16: Так
A17: Інтеграції | B17: З якими системами інтегруємось (EHR, платіжні шлюзи, банки, CRM)? | D17: Відкрите | E17: Так
A18: Інтеграції | B18: Чи є API і документація? Хто дає доступ до sandbox? | D18: Відкрите | E18: Так
A19: Інтеграції | B19: Існуюча система: що лишається, що замінюємо? | D19: Відкрите | E19: Так
... A33: Критерії успіху | B33: Що після запуску: підтримка, SLA, розвиток? | D33: Відкрите | E33: Так

Sheet Estimate
A1: Estimate (WBS)
A2: Декомпозиція робіт і оцінка в годинах. Scope живе тільки тут: колонки Scope (In/Out) і Припущення. Ціна оферу і Roadmap беруться звідси. Що означає кожна метрика, дивись у довідці праворуч (колонки N–O).
A4: Вхідні параметри | E4: Підсумки | N4: Довідка по метриках
B5: Ставка, $/год | C5: 40 | D5: Джерело: внутрішня ставка компанії | E5: PERT In scope, год | F5: =SUMIFS(H11:H500,K11:K500,"In") -> 12.666667 | N5: Метрика | O5: Що означає і навіщо
B6: Буфер на ризики | C6: 0.15 | D6: Джерело: рішення PM, залежить від невизначеності | E6: Out of scope, год | F6: =SUMIFS(I11:I500,K11:K500,"Out") -> 0 | N6: Ставка, $/год | O6: Скільки коштує година роботи для клієнта. Множник для всіх грошових сум.
B7: Разом In scope, год (з буфером) | C7: =SUMIFS(I11:I500,K11:K500,"In") -> 14.566667 | E7: Діапазон In scope, год (Min) | F7: =SUMIFS(E11:E500,K11:K500,"In") -> 8 | N7: Буфер на ризики | O7: Відсоток зверху на невідоме: уточнення вимог, баги, комунікацію. 10–15% для зрозумілого проєкту, 20–30% для нового домену або складних інтеграцій.
B8: Ціна оферу, $ | C8: =C7*C5 -> 582.66667 | E8: Діапазон In scope, год (Max) | F8: =SUMIFS(G11:G500,K11:K500,"In") -> 20 | N8: Min, год | O8: Оптимістична оцінка: все йде гладко, вимоги зрозумілі.
N9: Likely, год | O9: Найімовірніша оцінка: як зазвичай буває на схожих задачах.
A10: WBS ID | B10: Етап / Epic | C10: Задача | D10: Роль | E10: Min, год | F10: Likely, год | G10: Max, год | H10: PERT, год | I10: З буфером, год | J10: Вартість, $ | K10: Scope | L10: Припущення / коментар | N10: Max, год | O10: Песимістична оцінка: проблеми з API, переробки, неточні вимоги. Не катастрофа, а реалістичний поганий сценарій.
A11: 1.1 | B11: Авторизація | C11: Приклад: логін через email + 2FA | D11: Backend | E11: 8 | F11: 12 | G11: 20 | H11: =IF(COUNT(E11:G11)<3,"",(E11+4*F11+G11)/6) -> 12.666667 | I11: =IF(H11="","",H11*(1+$C$6)) -> 14.566667 | J11: =IF(I11="","",I11*$C$5) -> 582.66667 | K11: In | L11: Використовуємо Auth0, без кастомного SSO | N11: PERT, год | O11: Зважене середнє (Min + 4×Likely + Max) / 6. Likely має найбільшу вагу, але широкий діапазон тягне оцінку вгору. Так ризик задачі потрапляє в цифру.
K12: In | N12: З буфером, год | O12: PERT × (1 + Буфер на ризики). Години, які йдуть у ціну оферу.
H13: =IF(COUNT(E13:G13)<3,"",(E13+4*F13+G13)/6) | I13: =IF(H13="","",H13*(1+$C$6)) | J13: =IF(I13="","",I13*$C$5) | N13: Вартість, $ | O13: З буфером × Ставка. Ціна задачі для клієнта.
H14: =IF(COUNT(E14:G14)<3,"",(E14+4*F14+G14)/6) | I14: =IF(H14="","",H14*(1+$C$6)) | J14: =IF(I14="","",I14*$C$5) | N14: Scope | O14: In означає входить в офер і рахується в підсумках. Out означає обговорили, але не робимо; фіксується, щоб не було суперечок пізніше.
H15: =IF(COUNT(E15:G15)<3,"",(E15+4*F15+G15)/6) | I15: =IF(H15="","",H15*(1+$C$6)) | J15: =IF(I15="","",I15*$C$5) | N15: Припущення | O15: На чому тримається оцінка задачі (наприклад, «використовуємо Auth0»). Якщо припущення ламається, це підстава для Change Log.
H16: =IF(COUNT(E16:G16)<3,"",(E16+4*F16+G16)/6) | I16: =IF(H16="","",H16*(1+$C$6)) | J16: =IF(I16="","",I16*$C$5) | N16: Разом In scope (з буфером) | O16: Сума годин з буфером по задачах In. Іде в ціну оферу і на лист Overview.
H17: =IF(COUNT(E17:G17)<3,"",(E17+4*F17+G17)/6) | I17: =IF(H17="","",H17*(1+$C$6)) | J17: =IF(I17="","",I17*$C$5) | N17: Ціна оферу, $ | O17: Разом In scope × Ставка. Цифра для Proposal.
H18: =IF(COUNT(E18:G18)<3,"",(E18+4*F18+G18)/6) | I18: =IF(H18="","",H18*(1+$C$6)) | J18: =IF(I18="","",I18*$C$5) | N18: PERT In scope | O18: Сума без буфера. Різниця з «Разом» показує, скільки годин закладено на ризики.
H19: =IF(COUNT(E19:G19)<3,"",(E19+4*F19+G19)/6) | I19: =IF(H19="","",H19*(1+$C$6)) | J19: =IF(I19="","",I19*$C$5) | N19: Out of scope | O19: Обсяг робіт, які свідомо винесли за рамки. Кандидати на наступну фазу або допродаж.
H20: =IF(COUNT(E20:G20)<3,"",(E20+4*F20+G20)/6) | I20: =IF(H20="","",H20*(1+$C$6)) | J20: =IF(I20="","",I20*$C$5) | N20: Діапазон Min / Max | O20: Найкращий і найгірший сценарій по проєкту. Допомагає пояснити клієнту, чому оцінка не одна цифра, і перевірити, що ціна оферу не нижча за реалістичний результат.
H21: =IF(COUNT(E21:G21)<3,"",(E21+4*F21+G21)/6) | I21: =IF(H21="","",H21*(1+$C$6)) | J21: =IF(I21="","",I21*$C$5) | N21: Демо / презентації | O21: Обов'язковий рядок WBS 0.1. Демо по кожному milestone: що показуємо, на якому середовищі, з якими даними. Етап закрито, коли клієнт готовий до наступного кроку: результат прийнято або він питає «що далі».
H22: =IF(COUNT(E22:G22)<3,"",(E22+4*F22+G22)/6) | I22: =IF(H22="","",H22*(1+$C$6)) | J22: =IF(I22="","",I22*$C$5)
H23: =IF(COUNT(E23:G23)<3,"",(E23+4*F23+G23)/6) | I23: =IF(H23="","",H23*(1+$C$6)) | J23: =IF(I23="","",I23*$C$5)
H24: =IF(COUNT(E24:G24)<3,"",(E24+4*F24+G24)/6) | I24: =IF(H24="","",H24*(1+$C$6)) | J24: =IF(I24="","",I24*$C$5)
H25: =IF(COUNT(E25:G25)<3,"",(E25+4*F25+G25)/6) | I25: =IF(H25="","",H25*(1+$C$6)) | J25: =IF(I25="","",I25*$C$5)
H26: =IF(COUNT(E26:G26)<3,"",(E26+4*F26+G26)/6) | I26: =IF(H26="","",H26*(1+$C$6)) | J26: =IF(I26="","",I26*$C$5)
H27: =IF(COUNT(E27:G27)<3,"",(E27+4*F27+G27)/6) | I27: =IF(H27="","",H27*(1+$C$6)) | J27: =IF(I27="","",I27*$C$5)
H28: =IF(COUNT(E28:G28)<3,"",(E28+4*F28+G28)/6) | I28: =IF(H28="","",H28*(1+$C$6)) | J28: =IF(I28="","",I28*$C$5)
H29: =IF(COUNT(E29:G29)<3,"",(E29+4*F29+G29)/6) | I29: =IF(H29="","",H29*(1+$C$6)) | J29: =IF(I29="","",I29*$C$5)
H30: =IF(COUNT(E30:G30)<3,"",(E30+4*F30+G30)/6) | I30: =IF(H30="","",H30*(1+$C$6)) | J30: =IF(I30="","",I30*$C$5)
H31: =IF(COUNT(E31:G31)<3,"",(E31+4*F31+G31)/6) | I31: =IF(H31="","",H31*(1+$C$6)) | J31: =IF(I31="","",I31*$C$5)
H32: =IF(COUNT(E32:G32)<3,"",(E32+4*F32+G32)/6) | I32: =IF(H32="","",H32*(1+$C$6)) | J32: =IF(I32="","",I32*$C$5)
H33: =IF(COUNT(E33:G33)<3,"",(E33+4*F33+G33)/6) | I33: =IF(H33="","",H33*(1+$C$6)) | J33: =IF(I33="","",I33*$C$5)
... H210: =IF(COUNT(E210:G210)<3,"",(E210+4*F210+G210)/6) | I210: =IF(H210="","",H210*(1+$C$6)) | J210: =IF(I210="","",I210*$C$5)

Sheet Roadmap
A1: Roadmap / Project Plan
A2: Етапи і milestones, зібрані з WBS. Залежності показують, що блокує старт етапу. Milestone з оплатою прив'язує гроші до результату (для Fixed Price). Демо обов'язкове для кожного milestone: план демо заповнюється до старту етапу (червона клітинка означає, що його немає). Етап закрито, коли клієнт готовий до наступного кроку: результат прийнято або він питає «що далі».
A4: Етап / Milestone | B4: WBS ID | C4: Результат (що отримує клієнт) | D4: Початок | E4: Кінець | F4: Тривалість, днів | G4: Залежить від | H4: Відповідальний | I4: Статус | J4: Оплата за milestone, $ | K4: Демо: що показуємо і як | L4: Дата демо | M4: Результат демо
A5: M1: Авторизація | B5: 1.1–1.4 | C5: Приклад: користувач реєструється і входить з 2FA на staging | D5: 46328 | E5: 46339 | F5: =IF(OR(D5="",E5=""),"",NETWORKDAYS(D5,E5)) -> 10 | G5: Доступи до Auth0 | H5: Backend lead | I5: Заплановано | J5: 2000 | K5: Приклад: живий прохід на staging: реєстрація → вхід з 2FA під тестовим акаунтом клієнта | L5: 46339 | M5: Заплановано
F6: =IF(OR(D6="",E6=""),"",NETWORKDAYS(D6,E6))
F7: =IF(OR(D7="",E7=""),"",NETWORKDAYS(D7,E7))
F8: =IF(OR(D8="",E8=""),"",NETWORKDAYS(D8,E8))
F9: =IF(OR(D9="",E9=""),"",NETWORKDAYS(D9,E9))
F10: =IF(OR(D10="",E10=""),"",NETWORKDAYS(D10,E10))
F11: =IF(OR(D11="",E11=""),"",NETWORKDAYS(D11,E11))
F12: =IF(OR(D12="",E12=""),"",NETWORKDAYS(D12,E12))
F13: =IF(OR(D13="",E13=""),"",NETWORKDAYS(D13,E13))
F14: =IF(OR(D14="",E14=""),"",NETWORKDAYS(D14,E14))
F15: =IF(OR(D15="",E15=""),"",NETWORKDAYS(D15,E15))
F16: =IF(OR(D16="",E16=""),"",NETWORKDAYS(D16,E16))
F17: =IF(OR(D17="",E17=""),"",NETWORKDAYS(D17,E17))
... F204: =IF(OR(D204="",E204=""),"",NETWORKDAYS(D204,E204))

Sheet Backlog
A1: Backlog
A2: Задачі для команди. Кожна прив'язана до WBS ID, щоб бачити, скільки оцінки вже витрачено. Якщо ведете задачі в Jira, тут лише посилання і план/факт годин. Для кожної задачі типу Feature обов'язково вирішити, чи показуємо її на демо (червона клітинка означає, що не вирішено). Фіча закрита для клієнта, коли її показали на демо, а не коли статус Done.
A4: Оцінка, год | B4: =SUM(I7:I500) -> 6 | C4: Факт, год | D4: =SUM(J7:J500) -> 7 | E4: Факт / оцінка | F4: =IF(B4=0,0,D4/B4) -> 1.1666667
A6: ID | B6: WBS ID | C6: Задача | D6: Тип | E6: Пріоритет | F6: Статус | G6: Виконавець | H6: Спринт | I6: Оцінка, год | J6: Факт, год | K6: Посилання | L6: На демо | M6: Показано на демо
A7: B-1 | B7: 1.1 | C7: Приклад: API ендпоінт /auth/login | D7: Feature | E7: High | F7: Done | G7: Олег | H7: S1 | I7: 6 | J7: 7 | K7: https://jira.example.com/B-1 | L7: Так | M7: 46339

Sheet Access & Env
A1: Access & Environments
A2: Обов'язковий чекліст на старті і при зміні команди. Паролі, ключі й токени сюди не пишемо: тільки де вони лежать (менеджер паролів, vault).
A4: Не отримано | B4: =COUNTIF(G7:G500,"Запитано")+COUNTIF(G7:G500,"Не запитано") -> 16
A6: Ресурс | B6: Тип | C6: Середовище | D6: URL | E6: Хто надає | F6: Хто має доступ | G6: Статус | H6: Дата | I6: Примітка
A7: Репозиторій | B7: Code | C7: — | G7: Не запитано
A8: CI/CD | B8: DevOps | C8: — | G8: Не запитано
A9: Dev середовище | B9: Environment | C9: Dev | G9: Не запитано
A10: Staging середовище | B10: Environment | C10: Stage | G10: Не запитано
A11: Production середовище | B11: Environment | C11: Prod | G11: Не запитано
A12: Хмарна консоль (AWS/GCP/Azure) | B12: Cloud | C12: — | G12: Не запитано
A13: База даних | B13: Data | C13: Dev | G13: Не запитано
A14: Трекер задач | B14: Tool | C14: — | G14: Не запитано
A15: Канал комунікації | B15: Tool | C15: — | G15: Не запитано
A16: Дизайн (Figma) | B16: Tool | C16: — | G16: Не запитано
A17: API ключі сторонніх сервісів | B17: Integration | C17: Dev | G17: Не запитано
A18: Sandbox платіжного шлюзу / EHR | B18: Integration | C18: Dev | G18: Не запитано
... A22: BAA / DPA підписані | B22: Compliance | C22: — | G22: Не запитано

Sheet Daily Report
A1: Daily Report
A2: Коли клієнт просить щоденні апдейти. Один рядок на людину на день. Блокери з цього листа, що живуть довше дня, переносяться в Weekly Report як ризики.
A4: Дата | B4: Хто | C4: Зроблено | D4: План | E4: Message from the client | F4: Год | G4: Посилання (PR, задачі)
A5: 2026-10-14 | B5: Олег | C5: Приклад: ендпоінт логіну, тести | D5: 2FA через SMS | F5: 7 | G5: B-1, PR #12

Sheet Weekly Report
A1: Weekly Report
A2: Щотижневий звіт клієнту за фактом виконаної роботи. Один рядок на тиждень. Блок «Що потрібно від клієнта» найважливіший: так блокери стають видимими для того, хто може їх зняти.
A4: Тиждень з | B4: Тиждень по | C4: Статус (RAG) | D4: Що зробили | E4: Закриті фічі | F4: План на наступний тиждень | G4: Ризики | H4: Що потрібно від клієнта | I4: Год за тиждень | J4: Год всього | K4: Відправлено
A5: 2026-11-02 | B5: 2026-11-06 | C5: Жовтий | D5: Приклад: авторизація на staging, 70% тестів | E5: Логін, реєстрація | F5: 2FA, відновлення пароля | G5: Затримка доступу до SMS-провайдера | H5: Доступ до Twilio до середи | I5: 78 | J5: =IF(I5="","",SUM($I$5:I5)) -> 78 | K5: 2026-11-06
J6: =IF(I6="","",SUM($I$5:I6))
J7: =IF(I7="","",SUM($I$5:I7))
J8: =IF(I8="","",SUM($I$5:I8))
J9: =IF(I9="","",SUM($I$5:I9))
J10: =IF(I10="","",SUM($I$5:I10))
J11: =IF(I11="","",SUM($I$5:I11))
J12: =IF(I12="","",SUM($I$5:I12))
J13: =IF(I13="","",SUM($I$5:I13))
J14: =IF(I14="","",SUM($I$5:I14))
J15: =IF(I15="","",SUM($I$5:I15))
J16: =IF(I16="","",SUM($I$5:I16))
J17: =IF(I17="","",SUM($I$5:I17))
... J204: =IF(I204="","",SUM($I$5:I204))

Sheet Change Log
A1: Change Log
A2: Кожна зміна scope після оферу: що змінилось і скільки це коштує в годинах, грошах і днях. Без цього листа оцінка застаріває, і зсув дедлайну неможливо пояснити клієнту.
A4: Затверджено, год | B4: =SUMIFS(E8:E500,H8:H500,"Затверджено") -> 16
A5: Затверджено, $ | B5: =SUMIFS(F8:F500,H8:H500,"Затверджено") -> 640
A7: CR ID | B7: Дата | C7: Запит | D7: Ініціатор | E7: Вплив, год | F7: Вплив, $ | G7: Вплив на дедлайн, днів | H7: Рішення | I7: Дата рішення | J7: WBS ID
A8: CR-1 | B8: 2026-11-10 | C8: Приклад: вхід через Google | D8: Клієнт | E8: 16 | F8: =IF(E8="","",E8*Estimate!$C$5) -> 640 | G8: 3 | H8: Затверджено | I8: 2026-11-11 | J8: 1.5
F9: =IF(E9="","",E9*Estimate!$C$5)
F10: =IF(E10="","",E10*Estimate!$C$5)
F11: =IF(E11="","",E11*Estimate!$C$5)
F12: =IF(E12="","",E12*Estimate!$C$5)
F13: =IF(E13="","",E13*Estimate!$C$5)
F14: =IF(E14="","",E14*Estimate!$C$5)
F15: =IF(E15="","",E15*Estimate!$C$5)
F16: =IF(E16="","",E16*Estimate!$C$5)
F17: =IF(E17="","",E17*Estimate!$C$5)
F18: =IF(E18="","",E18*Estimate!$C$5)
F19: =IF(E19="","",E19*Estimate!$C$5)
F20: =IF(E20="","",E20*Estimate!$C$5)
... F207: =IF(E207="","",E207*Estimate!$C$5)

Sheet Project Notes
A1: Project Notes
A2: Журнал PM на весь проєкт: дзвінки, рішення, питання, ідеї. Рішення фіксуються тут з датою, щоб через місяць було видно, хто і чому погодив.
A4: Дата | B4: Тип | C4: Учасники | D4: Зміст | E4: Рішення / Action items | F4: Відповідальний | G4: Дедлайн | H4: Статус
A5: 2026-10-14 | B5: Дзвінок | C5: Клієнт (CTO), PM | D5: Приклад: обговорили інтеграції з EHR | E5: Клієнт дає доступ до sandbox до 20.10 | F5: Клієнт | G5: 2026-10-20 | H5: Відкрите
